{"version":"0.0.0","description":"Behavioral verification CLI for AI development workflows","homepage":"https://github.com/charly-vibes/espectacular","license":"MIT","url":"https://github.com/charly-vibes/espectacular/releases/download/v0.0.0/ah_0.0.0_windows_amd64.zip","hash":"sha256:0000000000000000000000000000000000000000000000000000000000000000","bin":"ah.exe","checkver":{"github":"https://github.com/charly-vibes/espectacular"},"autoupdate":{"url":"https://github.com/charly-vibes/espectacular/releases/download/v$version/ah_$version_windows_amd64.zip"},"from":"https://github.com/charly-vibes/scoop-charly"}
