{
    "version": "4.11.0",
    "description": "集找番、追番、看番的一站式弹幕追番平台，云收藏同步 (Bangumi)，离线缓存，BitTorrent，弹幕云过滤。",
    "homepage": "https://myani.org/",
    "license": "AGPL-3.0-only",
    "architecture": {
        "64bit": {
            "url": "https://github.com/open-ani/ani/releases/download/v4.11.0/ani-4.11.0-windows-x86_64.zip",
            "hash": "777bb013a93f24420f2cf72f4710a0c5491709e49585f0c9e76827dec533f6cd",
            "extract_dir": "Ani"
        }
    },
    "shortcuts": [
        [
            "Ani.exe",
            "Ani"
        ]
    ],
    "checkver": {
        "github": "https://github.com/open-ani/ani"
    },
    "autoupdate": {
        "architecture": {
            "64bit": {
                "url": "https://github.com/open-ani/ani/releases/download/v$version/ani-$version-windows-x86_64.zip"
            }
        },
        "hash": {
            "mode": "download"
        }
    }
}
