{
    "version": "1.0",
    "description": "Streamlined MS Store App Fetcher",
    "homepage": "https://github.com/Ameliorated-LLC/appfetch",
    "license": "MIT",
    "url": "https://github.com/Ameliorated-LLC/appfetch/releases/download/v1.0/appfetch.exe",
    "hash": "3c0be969b505919a04830e0506a0aece7ba878e4ed4ac3ddab64b74b0fd1ebdb",
    "bin": "appfetch.exe",
    "shortcuts": [
        ["appfetch.exe", "App Fetch"]
    ],
    "checkver": "github",
    "autoupdate": {
        "url": "https://github.com/Ameliorated-LLC/appfetch/releases/download/v$version/appfetch.exe"
    }
}
