{
    "version": "1.0.1",
    "description": "Utility that creates ICNS and ICO files from a PNG file",
    "homepage": "https://github.com/Orphoros/AppIconGen",
    "license":
    {
        "identifier": "GPL-3.0-only",
        "url": "https://github.com/Orphoros/AppIconGen/blob/main/LICENSE"
    },
    "architecture": {
        "64bit": {
            "url": "https://github.com/Orphoros/AppIconGen/releases/download/v1.0.1/appicongen.x86_64-pc-windows-msvc.zip",
            "hash": "065dce76019c87661c4b8eee6ba19218d559c830ce70f24ec756d5916df87381"
        }
    },
    "bin": [ [ "appicongen.exe", "appicongen" ] ],
    "checkver": {
        "github": "https://github.com/Orphoros/AppIconGen"
    },
    "autoupdate": {
        "architecture": {
            "64bit": {
                "url": "https://github.com/Orphoros/AppIconGen/releases/download/v$version/appicongen.x86_64-pc-windows-msvc.zip"
            }
        }
    }
}
