{
    "$schema": "https://raw.githubusercontent.com/lukesampson/scoop/master/schema.json",
    "##": "prefer the exe version as is more complete than basic zip",
    "version": "2025.10.31",
    "description": "astronomical stacking program, plate solver, and fits file viewer",
    "homepage": "https://www.hnsky.org/astap.htm",
    "license": "GPL-3.0-or-later",
    "notes": "Recommend install STAR database, such as smaller D05 or D20, large D50, or very large D80, or other databases depending on use case.",
    "architecture": {
        "64bit": {
            "url": "https://www.hnsky.org/astap_setup.exe",
            "hash": "c840d2a93be86897b480823cd0e6a8552811b3c7a1ba1e970720459b0d508ab0"
        },
        "32bit": {
            "url": "https://www.hnsky.org/astapwin32.zip",
            "hash": "ee45bf0c7c1ba6b9f1e8a26aec16e64d7f1a7f5e5bff66c2d2f76f12ed956927"
        }
    },
    "innosetup": true,
    "bin": [
        "astap_cli.exe",
        "dcraw.exe",
        "unprocessed_raw.exe"
    ],
    "shortcuts": [
        [
            "astap.exe",
            "Astrometric stacking program"
        ]
    ],
    "checkver": {
        "url": "https://www.hnsky.org/astap.htm",
        "regex": "ASTAP_installer.*_?v(\\d+\\.\\d+\\.\\d+)"
    },
    "autoupdate": {
        "architecture": {
            "64bit": {
                "url": "https://www.hnsky.org/astap_setup.exe"
            },
            "32bit": {
                "url": "https://www.hnsky.org/astapwin32.zip"
            }
        }
    }
}
