{"version":"0.11.24","description":"一个极其快速的 Python 包和项目管理器，用 Rust 编写 | An extremely fast Python package and project manager, written in Rust","homepage":"https://docs.astral.sh/uv/","license":{"identifier":"Apache-2.0|MIT"},"architecture":{"64bit":{"url":"https://github.com/astral-sh/uv/releases/download/0.11.24/uv-x86_64-pc-windows-msvc.zip","hash":"af9573a2e36f7020b18ec5fdde20117aae74bbad3f4acb3dc3fc03319f1aa083"},"arm64":{"url":"https://github.com/astral-sh/uv/releases/download/0.11.24/uv-aarch64-pc-windows-msvc.zip","hash":"51bcf8051dcc2075fba9136ece0f229205a6ef813e68e5709c6eeb18802afed5"}},"extract_to":"app","env_set":{"UV_PYTHON_INSTALL_DIR":"$persist_dir\\AppData\\Roaming\\uv\\python","UV_TOOL_DIR":"$persist_dir\\AppData\\Roaming\\uv\\tools","UV_CACHE_DIR":"$persist_dir\\AppData\\Local\\uv\\cache"},"env_add_path_expand":"$home\\.local\\bin","bin":["app\\uv.exe","app\\uvx.exe","app\\uvw.exe"],"link":["$env:AppData\\uv","$env:LocalAppData\\uv"],"pre_install":["if (!$bucket) { $bucket = (scoop config).'abgox-abyss-bucket-name' }",". $bucketsdir\\$bucket\\util\\1.ps1","A-Start-Install"],"post_install":["if (!$bucket) { $bucket = (scoop config).'abgox-abyss-bucket-name' }",". $bucketsdir\\$bucket\\util\\1.ps1","A-Complete-Install"],"pre_uninstall":["if (!$bucket) { $bucket = (scoop config).'abgox-abyss-bucket-name' }",". $bucketsdir\\$bucket\\util\\1.ps1","A-Start-Uninstall","A-Remove-Link","A-Stop-Process"],"post_uninstall":["if (!$bucket) { $bucket = (scoop config).'abgox-abyss-bucket-name' }",". $bucketsdir\\$bucket\\util\\1.ps1","A-Complete-Uninstall"],"checkver":{"script":[". $pwd\\util\\1.ps1","A-Get-VersionFromGithub"],"regex":"(.+)"},"autoupdate":{"architecture":{"64bit":{"url":"https://github.com/astral-sh/uv/releases/download/$version/uv-x86_64-pc-windows-msvc.zip"},"arm64":{"url":"https://github.com/astral-sh/uv/releases/download/$version/uv-aarch64-pc-windows-msvc.zip"}},"hash":{"mode":"github"}},"from":"https://github.com/abgox/abyss"}
