{
    "version": "1.0",
    "license": "unknown",
    "homepage": "https://palmdb.net/app/astraware-bang-bang",
    "url": [
        "https://palmdb.net/content/files/games-arcade/astraware-bang-bang/BangBang.prc",
        "https://palmcom.tripod.com/stuff/OS_Icons.zip"
    ],
    "hash": [
        "f184f2044367e1a435dfa5bdcc71801b8f341c4b8bdddc03d67a9891e69d39f2",
        "e3aad7b7a710b5d72b914a1d82ce741e52cdf9aeb4974f7c8afe2d7e8de07bb5"
    ],
    "depends": ["extras/retroarch", "filip2cz_scoop-retro/retroarch-mu_libretro", "filip2cz_scoop-retro/palmos41-en-m515_rom"],
    "pre_install": [
        "Set-Content -Path '~\\scoop\\apps\\BangBang\\1.0\\run.bat' -Value '%userprofile%\\scoop\\apps\\retroarch\\current\\retroarch.exe -L %userprofile%\\scoop\\apps\\retroarch\\current\\cores\\mu_libretro.dll %userprofile%\\scoop\\apps\\BangBang\\current\\BangBang.prc'"
    ],
    "shortcuts": [
        [
            "run.bat",
            "Bang! Bang!"
        ]
    ],
    "post_install":[
        "$shortcutPath = Join-Path $env:USERPROFILE 'AppData\\Roaming\\Microsoft\\Windows\\Start Menu\\Programs\\Scoop Apps\\Bang! Bang!.lnk'; $iconPath = Join-Path $env:USERPROFILE 'scoop\\apps\\BangBang\\current\\PalmOS.ico'; $shell = New-Object -ComObject WScript.Shell; $shortcut = $shell.CreateShortcut($shortcutPath); $shortcut.IconLocation = $iconPath; $shortcut.Save()"
    ]
}
