{"version":"0.2.2","description":"Boso AI — self-hosted coding agent. Your box, your model.","homepage":"https://boso.com","license":"Proprietary","url":"https://ai.boso.com/releases/boso-0.2.2.pyz","hash":"67b0232359ced785a23ccf8d7761e4bcea1c3e6f2efbd51f822cddcf2466b3cc","depends":["python"],"bin":[["boso-0.2.2.pyz","boso"]],"checkver":{"url":"https://ai.boso.com/releases/","regex":"boso-([\\d.]+)\\.pyz"},"autoupdate":{"url":"https://ai.boso.com/releases/boso-$version.pyz"},"from":"https://github.com/Arama0517/scoop-bucket"}
