{
    "version": "151.0.7873.0",
    "description": "Fast, secure, and free web browser, built for the modern web.",
    "homepage": "https://www.google.com/chrome/canary",
    "license": {
        "identifier": "Freeware",
        "url": "https://www.google.com/chrome/privacy/eula_text.html"
    },
    "architecture": {
        "64bit": {
            "url": "https://dl.google.com/release2/chrome/ac4i7m7whmi4edsh3kslwztjba3a_151.0.7873.0/151.0.7873.0_chrome_installer_uncompressed.exe#/dl.7z",
            "hash": "5004527cfad960cd668a4b04ad04f2134c7450035b384b48f3a3310b0c4b55cd"
        },
        "32bit": {
            "url": "https://dl.google.com/release2/chrome/hriejw7b467iyauqx3ab7fcacy_151.0.7873.0/151.0.7873.0_chrome_installer_uncompressed.exe#/dl.7z",
            "hash": "b4630c0cefef8b88772616676a12347776576eb71f6115452472f3ef3b62c26d"
        }
    },
    "extract_dir": "Chrome-bin",
    "bin": [
        [
            "chrome.exe",
            "chrome"
        ]
    ],
    "shortcuts": [
        [
            "chrome.exe",
            "Google Chrome"
        ]
    ],
    "checkver": {
        "url": "https://scoopinstaller.github.io/UpdateTracker/googlechrome/chrome.min.xml",
        "regex": "(?sm)<canary32><version>(?<version>[\\d.]+)</version>.+release2/chrome/(?<32>[\\w-]+)_.+<canary64>.+release2/chrome/(?<64>[\\w-]+)_.+</canary64>"
    },
    "autoupdate": {
        "architecture": {
            "64bit": {
                "url": "https://dl.google.com/release2/chrome/$match64_$version/$version_chrome_installer_uncompressed.exe#/dl.7z",
                "hash": {
                    "url": "https://scoopinstaller.github.io/UpdateTracker/googlechrome/chrome.min.xml",
                    "xpath": "/chromechecker/canary64[version='$version']/sha256"
                }
            },
            "32bit": {
                "url": "https://dl.google.com/release2/chrome/$match32_$version/$version_chrome_installer_uncompressed.exe#/dl.7z",
                "hash": {
                    "url": "https://scoopinstaller.github.io/UpdateTracker/googlechrome/chrome.min.xml",
                    "xpath": "/chromechecker/canary32[version='$version']/sha256"
                }
            }
        }
    }
}
