{"version":"2.3.15","description":"一个强大的 AI IDE | A powerful AI IDE","homepage":"https://windsurf.com/","license":{"identifier":"Unknown","url":"https://windsurf.com/terms-of-service-individual"},"architecture":{"64bit":{"url":"https://windsurf-stable.codeiumdata.com/win32-x64-user/stable/c46c49e94b4d3f41181204d59809d8f1b2c48d68/WindsurfUserSetup-x64-2.3.15.exe","hash":"d5c38c53bd6152401d979873875f2a92d880720402037c340fafdaa5ffbd5ea1"}},"env_add_path":"app\\bin","commands":"windsurf","shortcuts":[["app\\Windsurf.exe","Windsurf"]],"link":["$env:AppData\\Windsurf","$home\\.windsurf"],"pre_install":["if (!$bucket) { $bucket = (scoop config).'abgox-abyss-bucket-name' }",". $bucketsdir\\$bucket\\util\\1.ps1","A-Start-Install","A-Install-Inno"],"post_install":["if (!$bucket) { $bucket = (scoop config).'abgox-abyss-bucket-name' }",". $bucketsdir\\$bucket\\util\\1.ps1","A-Complete-Install"],"pre_uninstall":["if (!$bucket) { $bucket = (scoop config).'abgox-abyss-bucket-name' }",". $bucketsdir\\$bucket\\util\\1.ps1","A-Start-Uninstall","A-Stop-Process","A-Remove-Link","A-Uninstall-Inno"],"post_uninstall":["if (!$bucket) { $bucket = (scoop config).'abgox-abyss-bucket-name' }",". $bucketsdir\\$bucket\\util\\1.ps1","A-Complete-Uninstall"],"checkver":{"script":[". $pwd\\util\\1.ps1","$res, $out = A-Get-InstallerInfoFromWinget 'Codeium.Windsurf' 'exe'","$out"],"regex":"(?:.*ver:(?<version>[^;]+))(?:.*x64:(?<x64>[^;]+))?(?:.*x86:(?<x86>[^;]+))?(?:.*arm64:(?<arm64>[^;]+))?"},"autoupdate":{"architecture":{"64bit":{"url":"$matchX64","hash":{"url":"temp-autoupdate.json","jsonpath":"$.x64_user.InstallerSha256"}}}},"from":"https://github.com/abgox/abyss"}
