{
    "version": "0.7.4",
    "description": "Deder Build Tool",
    "homepage": "https://github.com/sake92/deder",
    "license": "Apache-2",
    "url": "https://github.com/sake92/deder/releases/download/v0.7.4/deder-client-windows-x86_64.zip",
    "hash": "sha256:037e411b43f04b4c77784a4fb1b10b92fc356a15cdd390d579f4cabe892a987a",
    "bin": "deder.exe",
    "checkver": {
        "url": "https://github.com/sake92/deder/releases/latest",
        "re": "v([\\d.]+)"
    },
    "autoupdate": {
        "url": "https://github.com/sake92/deder/releases/download/v$version/deder-client-windows-x86_64.zip",
        "hash": {
            "url": "$url.sha256"
        }
    }
}
