{
    "version": "12.23",
    "description": "Save and restore the desktop icon positions.",
    "homepage": "https://www.softwareok.com/?seite=Freeware/DesktopOK",
    "license": "https://www.softwareok.com/?seite=Freeware/DesktopOK/Eula",
    "architecture": {
        "64bit": {
            "url": "https://www.softwareok.com/Download/DesktopOK_x64.zip",
            "hash": "2c497f2ebfb111b523ec102efcd8a3bbbb5d6fc19c28d15026b43ef4cd8950c0"
        }
    },
    "shortcuts": [
        [
            "DesktopOK_x64.exe",
            "DesktopOK"
        ]
    ],
    "pre_install": [
        "$ini = \"DesktopOK.ini\"",
        "if (!(Test-Path \"$persist_dir\\$ini\")) {",
        "   New-Item -Path \"$dir\\$ini\" -ItemType File",
        " # Add-Content -Path \"$dir\\$ini\" -Value \"\" -Encoding Ascii",
        "}"
    ],
    "persist": "DesktopOK.ini",
    "checkver": {
        "url": "https://www.softwareok.com/?Download=DesktopOK",
        "regex": "Download DesktopOK (?<ver>[\\d.]+) for Microsoft Windows",
        "replace": "${ver}"
    },
    "autoupdate": {
        "architecture": {
            "64bit": {
                "url": "https://www.softwareok.com/Download/DesktopOK_x64.zip"
            }
        }
    }
}
