{
    "version": "0.8.2",
    "description": "Convenient UI for any drag & drop operations",
    "homepage": "https://github.com/drovp/drovp",
    "license": "Freeware",
    "architecture": {
        "64bit": {
            "url": "https://github.com/drovp/drovp/releases/download/0.8.2/Drovp-x64.zip",
            "hash": "487b1927405852fda45b3a260e0864e0a93e02e852c1830af2638b8de0a98322"
        }
    },
    "shortcuts": [
        [
            "Drovp.exe",
            "Drovp"
        ]
    ],
    "persist": "userData",
    "checkver": "github",
    "autoupdate": {
        "architecture": {
            "64bit": {
                "url": "https://github.com/drovp/drovp/releases/download/$version/Drovp-x64.zip"
            }
        }
    }
}
