{
    "version": "2.1.2",
    "description": "FAgram Desktop is a custom Telegram client.",
    "homepage": "https://github.com/burhancodes/fagramdesktop",
    "license": "GPL-3.0",
    "architecture": {
        "64bit": {
            "url": "https://github.com/burhancodes/fagramdesktop/releases/download/2.1.2/FAgram_Win-x64_2.1.2_portable.zip",
            "hash": "dac9c0c8a756fcdcfbc3de693c480eb146d60a89b09c4e6796d50d2e86f399cc"
        }
    },
    "shortcuts": [
        [
            "FAgram.exe",
            "FAgram"
        ]
    ],
    "persist": "tdata",
    "checkver": "github",
    "autoupdate": {
        "architecture": {
            "64bit": {
                "url": "https://github.com/burhancodes/fagramdesktop/releases/download/$version/FAgram_Win-x64_$version_portable.zip"
            }
        }
    }
}
