{
  "version": "0.6.8",
  "description": "The context layer for git",
  "homepage": "https://gitwhy.dev",
  "license": "MIT",
  "architecture": {
    "64bit": {
      "url": "https://dl.gitwhy.dev/v0.6.8/gitwhy_0.6.8_windows_amd64.zip",
      "hash": "e7e1279bb10d6e57bfc5116cc356261f03fc1da71f72f6df3f1b77ba0638e502"
    }
  },
  "bin": "git-why.exe",
  "checkver": {
    "url": "https://dl.gitwhy.dev/latest",
    "regex": "^([\\d.]+)$"
  },
  "autoupdate": {
    "architecture": {
      "64bit": {
        "url": "https://dl.gitwhy.dev/v$version/gitwhy_$version_windows_amd64.zip"
      }
    }
  }
}
