{
    "version": "2.5-DEV-rev1775-g792100e3",
    "description": "GPAC",
    "homepage": "https://gpac.wp.imt.fr",
    "license": "LGPL-2.1",
    "url": "https://download.tsi.telecom-paristech.fr/gpac/new_builds/win64/gpac-2.5-DEV-rev1775-g792100e3-master-x64.exe#/dl.7z",
    "hash": "69d6f79537de8526f58625ed21241c7f9ce00f3db4c2031a8147f3ed75a181f3",
    "bin": [
        "mp4box.exe",
        "gpac.exe"
    ],
    "checkver": {
        "url": "https://download.tsi.telecom-paristech.fr/gpac/new_builds/win64/",
        "regex": "gpac-([\\d.]+-DEV-rev\\d+-g[a-f\\d]+)-master-x64.exe"
    },
    "autoupdate": {
        "url": "https://download.tsi.telecom-paristech.fr/gpac/new_builds/win64/gpac-$version-master-x64.exe#/dl.7z"
    }
}
