{
    "version": "2.5-DEV-rev442-g03658744",
    "description": "GPAC",
    "homepage": "https://gpac.wp.imt.fr",
    "license": "LGPL-2.1",
    "url": "https://download.tsi.telecom-paristech.fr/gpac/new_builds/win64/gpac-2.5-DEV-rev442-g03658744-master-x64.exe#/dl.7z",
    "hash": "376537cdeda98bef2a025e9472bd4dea3c33e52adfbc896b31a67f277d778e9c",
    "bin": [
        "mp4box.exe",
        "gpac.exe"
    ],
    "checkver": {
        "url": "https://download.tsi.telecom-paristech.fr/gpac/new_builds/win64/",
        "regex": "gpac-([\\d.]+-DEV-rev\\d+-g[a-f\\d]+)-master-x64.exe"
    },
    "autoupdate": {
        "url": "https://download.tsi.telecom-paristech.fr/gpac/new_builds/win64/gpac-$version-master-x64.exe#/dl.7z"
    }
}
