{
    "version": "20241210-182559",
    "homepage": "https://www.deltaconnected.com/arcdps/",
    "architecture": {
        "64bit": {
            "url": "https://www.deltaconnected.com/arcdps/x64/d3d11.dll",
            "hash": "56c3218a129f3ec0a26034a24c8fdc4de8d0fc5f5d6477a59c10b752b8772479"
        }
    },
    "checkver": {
        "url": "https://www.deltaconnected.com/arcdps/",
        "regex": "here.*\\(([\\d-]+)\\)"
    },
    "autoupdate": {
        "architecture": {
            "64bit": {
                "url": "https://www.deltaconnected.com/arcdps/x64/d3d11.dll"
            }
        }
    }
}
