{
    "version": "2.186.5",
    "description": "Half-Life Advanced Effects (HLAE) is a tool to enrich Source (mainly CS:GO) engine based movie making.",
    "homepage": "https://github.com/advancedfx/advancedfx",
    "license": {
        "identifier": "MIT"
    },
    "url": "https://github.com/advancedfx/advancedfx/releases/download/v2.186.5/hlae_2_186_5.zip",
    "hash": "ec2a7e7972e1aab8ef313a5aa6d63049fdd9d675075e5ac8d80edb7ee8fa72ae",
    "bin": "HLAE.exe",
    "shortcuts": [
        [
            "HLAE.exe",
            "HLAE"
        ]
    ],
    "checkver": "github",
    "autoupdate": {
        "url": "https://github.com/advancedfx/advancedfx/releases/download/v$version/hlae_$underscoreVersion.zip"
    }
}
