{
    "version": "2.5.0",
    "description": "Fast, compact image and animation viewer. Can be used as a standalone application or integrated as a Total Commander Lister plugin.",
    "homepage": "https://www.nyam.pe.kr/dev/imagine/",
    "license": {
        "identifier": "Freeware",
        "url": "https://www.nyam.pe.kr/dev/imagine/#license"
    },
    "suggest": {
        "Total Commander Plugin Host": "extras/totalcommander"
    },
    "pre_install": "if (!(Test-Path \"$persist_dir\\Imagine.ini\")) { New-Item \"$dir\\Imagine.ini\" | Out-Null }",
    "architecture": {
        "64bit": {
            "url": "https://raw.githubusercontent.com/nyam1003/imagine/main/x64/Imagine_2.5.0_x64_Unicode_Full.zip",
            "hash": "889c9d7bb98d7d90edf13f96b54dc012f01132d95da005ff82e835e62453b23b",
            "bin": [
                "Imagine64.exe",
                [
                    "Imagine64.exe",
                    "Imagine"
                ]
            ],
            "shortcuts": [
                [
                    "Imagine64.exe",
                    "Imagine"
                ]
            ]
        },
        "32bit": {
            "url": "https://raw.githubusercontent.com/nyam1003/imagine/main/Imagine_2.5.0_Unicode_Full.zip",
            "hash": "984eb04c93bf369c3922295d2879c67256a02c7ec98e763048ce8bb2cee15a03",
            "bin": "Imagine.exe",
            "shortcuts": [
                [
                    "Imagine.exe",
                    "Imagine"
                ]
            ]
        }
    },
    "installer": {
        "script": [
            "$TCDir = $(appdir totalcommander $global)",
            "",
            "if ($TCDir -and (Test-Path \"$TCDir\\current\")) {",
            "    Write-Host \"Found Total Commander, integrating plugin...\" -ForegroundColor Cyan",
            "    ",
            "    $PluginDir = \"$TCDir\\current\\plugins\\Wlx\\Imagine\"",
            "    if (!(Test-Path \"$PluginDir\")) { New-Item \"$PluginDir\" -ItemType Directory -Force | Out-Null }",
            "    ",
            "    Copy-Item \"$dir\\*\" \"$PluginDir\" -Recurse -Force -Exclude \"Imagine.ini\", \"PlugInst.inf\"",
            "    Write-Host \"Imagine plugin installed to: $PluginDir\" -ForegroundColor Green",
            "} else {",
            "    Write-Host \"Total Commander (Scoop) not found. Installing as standalone application only.\" -ForegroundColor Yellow",
            "}"
        ]
    },
    "persist": [
        "Imagine.ini",
        "PlugInst.inf",
        "Plugin"
    ],
    "checkver": "v(\\d[\\d.]+)",
    "autoupdate": {
        "architecture": {
            "64bit": {
                "url": "https://raw.githubusercontent.com/nyam1003/imagine/main/x64/Imagine_$version_x64_Unicode_Full.zip"
            },
            "32bit": {
                "url": "https://raw.githubusercontent.com/nyam1003/imagine/main/Imagine_$version_Unicode_Full.zip"
            }
        }
    }
}
