{
    "version": "1.26.254",
    "description": "Irony Mod Manager",
    "homepage": "https://github.com/bcssov/IronyModManager/",
    "license": "GPL-3.0-or-later",
    "architecture": {
        "64bit": {
            "url": "https://github.com/bcssov/IronyModManager/releases/download/v1.26.254/win-x64.zip",
            "hash": "2a667cc4b9e20dd115648d82c8661cde2e94996dd83d7ad83246802d1faf1821"
        }
    },
    "bin": "IronyModManager.exe",
    "checkver": "github",
    "autoupdate": {
        "architecture": {
            "64bit": {
                "url": "https://github.com/bcssov/IronyModManager/releases/download/v$version/win-x64.zip"
            }
        }
    },
    "shortcuts": [
        [
            "IronyModManager.exe",
            "Irony Mod Manager"
        ]
    ]
}
