{
    "version": "0.0.22",
    "architecture": {
        "64bit": {
            "url": "https://github.com/gkwa/itmetrics/releases/download/v0.0.22/itmetrics_Windows_x86_64.zip",
            "bin": [
                "itmetrics.exe"
            ],
            "hash": "41937e69539bffc4da614e3426b6da772fe839c9797f0f43fa71d48b5342eb5b"
        }
    },
    "homepage": "https://github.com/gkwa/itmetrics",
    "license": "MIT",
    "description": "Description of the itmetrics project"
}
