{
  "version": "1.0.9",
  "description": "Watch movies and TV shows from terminal",
  "depends": ["fzf", "mpv", "yt-dlp", "chafa", "wezterm"],
  "homepage": "https://github.com/DemonKingSwarn/luffy",
  "license": "GPL-3.0",

  "architecture": {
    "64bit": {
      "url": "https://github.com/DemonKingSwarn/luffy/releases/download/v1.0.9/luffy-amd64.exe",
      "hash":  "bdad8eabcacc86c1dd1aca18320debf7d07c18ac511cac45507c16bd857ad988"
    }
  },

  "bin": [
    ["luffy-amd64.exe", "luffy"]
  ]
}
