{
    "version": "1.14.1",
    "description": "MaaEnd（终末地小助手）- 明日方舟：终末地全自动辅助工具",
    "homepage": "https://github.com/maaend/maaend",
    "license": "AGPL-3.0-or-later",
    "architecture": {
        "64bit": {
            "url": "https://github.com/maaend/maaend/releases/download/v1.14.1/MaaEnd-win-x86_64-v1.14.1.zip",
            "hash": "b9f4fb79db03086a0b0682ecb7fcc454b5a55f9cd742f4912309b455b1f732ac"
        },
        "arm64": {
            "url": "https://github.com/maaend/maaend/releases/download/v1.14.1/MaaEnd-win-aarch64-v1.14.1.zip",
            "hash": "59c093dd0eb4834c9729180a8282089ad1f1c472decb6dac08e8dd5ec3bae361"
        }
    },
    "pre_install": [
        "if (!(Test-Path \"$persist_dir\\config\")) {",
        "    New-Item -ItemType Directory -Path \"$persist_dir\\config\" -Force | Out-Null",
        "}",
        "if (!(Test-Path \"$persist_dir\\cache\")) {",
        "    New-Item -ItemType Directory -Path \"$persist_dir\\cache\" -Force | Out-Null",
        "}"
    ],
    "shortcuts": [
        [
            "MaaEnd.exe",
            "MaaEnd"
        ]
    ],
    "persist": [
        "config",
        "cache"
    ],
    "checkver": {
        "github": "https://github.com/maaend/maaend"
    },
    "autoupdate": {
        "architecture": {
            "64bit": {
                "url": "https://github.com/maaend/maaend/releases/download/v$version/MaaEnd-win-x86_64-v$version.zip"
            },
            "arm64": {
                "url": "https://github.com/maaend/maaend/releases/download/v$version/MaaEnd-win-aarch64-v$version.zip"
            }
        }
    }
}
