{
    "version": "1.244.1",
    "description": "MetaCubeXD",
    "homepage": "https://github.com/MetaCubeX/metacubexd",
    "license": "MIT",
    "url": "https://github.com/MetaCubeX/metacubexd/releases/download/v1.244.1/compressed-dist.tgz",
    "hash": "4edaa67e9255d1949d55fd481e6fb533e57a6df4924820bdfe5e9ceecac201b2",
    "post_install": [
        "if (Test-Path \"$scoopdir\\apps\\Mihomo\") {",
        "    if (!(Test-Path \"$scoopdir\\apps\\Mihomo\\current\\config\\ui\")) {",
        "        Remove-Item \"$scoopdir\\apps\\Mihomo\\current\\config\\ui\" -Force -Recurse",
        "    }",
        "    Copy-Item -Path \"$dir\" \"$scoopdir\\apps\\Mihomo\\current\\config\\ui\" -Recurse",
        "}"
    ],
    "checkver": "github",
    "autoupdate": {
        "url": "https://github.com/MetaCubeX/metacubexd/releases/download/v$version/compressed-dist.tgz"
    }
}
