{
    "version": "1.101.0",
    "description": "一个轻量级、功能强大，插件生态丰富的文件编辑器。Lightweight but powerful source code editor.",
    "homepage": "https://code.visualstudio.com/",
    "license": {
        "identifier": "Freeware",
        "url": "https://code.visualstudio.com/License/"
    },
    "notes": [
        "Add Visual Studio Code as a context menu option by running:",
        "reg import \"$dir\\install-context.reg\"",
        "For file associations, run:",
        "reg import \"$dir\\install-associations.reg\"",
        "For github integration, run:",
        "reg import \"$dir\\install-github-integration.reg\""
    ],
    "notes-cn": [
        "通过运行以下命令将 Visual Studio Code 添加到右键菜单选项：",
        "reg import \"$dir\\install-context.reg\"",
        "若要关联文件类型，请运行：",
        "reg import \"$dir\\install-associations.reg\"",
        "若要集成 GitHub，请运行：",
        "reg import \"$dir\\install-github-integration.reg\""
    ],
    "architecture": {
        "64bit": {
            "url": "https://update.code.visualstudio.com/1.101.0/win32-x64-archive/stable#/dl.7z",
            "hash": "88d54bb9f975643362d9e501c7bcab66880696f5fa3c213b3905cddd33999b1b"
        },
        "arm64": {
            "url": "https://update.code.visualstudio.com/1.101.0/win32-arm64-archive/stable#/dl.7z",
            "hash": "a8b958bd8d981540de6157ca7c4e8fcbb5db14b6b9c7542ec9f77f8fd22d6283"
        }
    },
    "env_add_path": "bin",
    "shortcuts": [
        [
            "code.exe",
            "Visual Studio Code"
        ]
    ],
    "pre_install": [
        ". \"$bucketsdir\\$bucket\\bin\\utils.ps1\"",
        "A-Start-PreInstall"
    ],
    "post_install": [
        ". \"$bucketsdir\\$bucket\\bin\\utils.ps1\"",
        "A-Start-PostInstall",
        "$LinkPaths = @(\"$env:AppData\\Code\",\"$env:UserProfile\\.vscode\")",
        "A-New-LinkDirectory $LinkPaths",
        "$dirpath = \"$dir\".Replace('\\', '\\\\')",
        "$exepath = \"$dir\\Code.exe\".Replace('\\', '\\\\')",
        "'install-associations', 'uninstall-associations', 'install-context', 'uninstall-context', 'install-github-integration', 'uninstall-github-integration' | ForEach-Object {",
        "  if (Test-Path \"$bucketsdir\\$bucket\\scripts\\vscode\\$_.reg\") {",
        "    $content = Get-Content \"$bucketsdir\\$bucket\\scripts\\vscode\\$_.reg\"",
        "    $content = $content.Replace('$codedir', $dirpath)",
        "    $content = $content.Replace('$code', $exepath)",
        "    if ($global) {",
        "      $content = $content.Replace('HKEY_CURRENT_USER', 'HKEY_LOCAL_MACHINE')",
        "    }",
        "    $content | Set-Content -Path \"$dir\\$_.reg\"",
        "  }",
        "}"
    ],
    "pre_uninstall": [
        "$bucket = $install.bucket",
        ". \"$bucketsdir\\$bucket\\bin\\utils.ps1\"",
        "A-Start-PreUninstall",
        "A-Stop-Process",
        "A-Remove-Link",
        "A-Remove-TempData @(\"$env:UserProfile\\.vscode\",\"$env:AppData\\Code\")"
    ],
    "post_uninstall": [
        "$bucket = $install.bucket",
        ". \"$bucketsdir\\$bucket\\bin\\utils.ps1\"",
        "A-Start-PostUninstall"
    ],
    "uninstaller": {
        "script": [
            "if ($cmd -eq 'uninstall')",
            "{",
            "   reg import \"$dir\\uninstall-context.reg\" ",
            "   reg import \"$dir\\uninstall-github-integration.reg\" ",
            "}"
        ]
    },
    "checkver": {
        "url": "https://update.code.visualstudio.com/api/update/win32-x64-archive/stable/latest",
        "jsonpath": "$.name"
    },
    "autoupdate": {
        "architecture": {
            "64bit": {
                "url": "https://update.code.visualstudio.com/$version/win32-x64-archive/stable#/dl.7z",
                "hash": {
                    "url": "https://update.code.visualstudio.com/api/update/win32-x64-archive/stable/latest",
                    "jsonpath": "$.sha256hash"
                }
            },
            "arm64": {
                "url": "https://update.code.visualstudio.com/$version/win32-arm64-archive/stable#/dl.7z",
                "hash": {
                    "url": "https://update.code.visualstudio.com/api/update/win32-arm64-archive/stable/latest",
                    "jsonpath": "$.sha256hash"
                }
            }
        }
    }
}
