{
    "$schema": "https://raw.githubusercontent.com/ScoopInstaller/Scoop/master/schema.json",
    "homepage": "https://www.mirc.com/",
    "version": "7.83",
    "description": "mIRC is a popular Internet Relay Chat client used by individuals and organizations to communicate, share, play and work with each other on IRC networks around the world. Serving the Internet community for over two decades, mIRC has evolved into a powerful, reliable and fun piece of technology.",
    "license": "Shareware",
    "url": "https://www.mirc.com/get.php#/dl.exe",
    "hash": "c4e001b16aefb94158c6ee0324491b843639548fe5facbb04a03f45b7e3847a9",
    "installer": {
        "args": [
            "/S",
            "/PORTABLE",
            "/NOSHORTCUT",
            "/NOUPDATE",
            "/D=$dir"
        ]
    },
    "uninstaller": {
        "file": "uninstall.exe",
        "args": [
            "/S"
        ]
    },
    "bin": [
        "mirc.exe"
    ],
    "shortcuts": [
        [
            "mirc.exe",
            "mIRC",
            "-noreg -r\"$dir\\config\""
        ]
    ],
    "persist": [
        "config",
        "download",
        "logs",
        "scripts",
        "sounds"
    ],
    "checkver": {
        "url": "https://www.mirc.com/versions.txt",
        "regex": "mIRC v(\\d+\\.\\d+)"
    },
    "autoupdate": {
        "url": "https://www.mirc.com/get.php#/dl.7z"
    }
}
