{
    "version": "0.1.5",
    "architecture": {
        "32bit": {
            "url": "https://github.com/mvisonneau/mmds/releases/download/v0.1.5/mmds_v0.1.5_windows_386.zip",
            "bin": [
                "mmds.exe"
            ],
            "hash": "ce93519775c417e20f04218ce6b116f429345ee8d9c796b499a2745eede3e2cb"
        },
        "64bit": {
            "url": "https://github.com/mvisonneau/mmds/releases/download/v0.1.5/mmds_v0.1.5_windows_amd64.zip",
            "bin": [
                "mmds.exe"
            ],
            "hash": "f7c99367712b8384532a0fcbd0c3b1320f492a84406534d792bcb57548c6aaa8"
        },
        "arm64": {
            "url": "https://github.com/mvisonneau/mmds/releases/download/v0.1.5/mmds_v0.1.5_windows_arm64.zip",
            "bin": [
                "mmds.exe"
            ],
            "hash": "3ca8624db3a0233402c3317563eda9c8fe0b6632d981ea64815dc5c349564ba5"
        }
    },
    "homepage": "https://github.com/mvisonneau/mmds",
    "license": "Apache 2.0",
    "description": "Missed (AWS) Meta-Data (service)"
}
