{
    "version": "2.10.0",
    "description": "Lossless MP3 volume adjustment - a modern mp3gain replacement written in Rust",
    "homepage": "https://github.com/M-Igashi/mp3rgain",
    "license": "MIT",
    "architecture": {
        "64bit": {
            "url": "https://github.com/M-Igashi/mp3rgain/releases/download/v2.10.0/mp3rgain-v2.10.0-windows-x86_64.zip",
            "hash": "b0149b4066778d0d76f476ba594464ac86106ce058aa9c2233daa98513824b10"
        },
        "arm64": {
            "url": "https://github.com/M-Igashi/mp3rgain/releases/download/v2.10.0/mp3rgain-v2.10.0-windows-arm64.zip",
            "hash": "dfc726abd2e81f99ee7937e5e13c519b42fdac4a663e1ca67457a5f0835c1e2c"
        }
    },
    "bin": "mp3rgain.exe",
    "checkver": "github",
    "autoupdate": {
        "architecture": {
            "64bit": {
                "url": "https://github.com/M-Igashi/mp3rgain/releases/download/v$version/mp3rgain-v$version-windows-x86_64.zip"
            },
            "arm64": {
                "url": "https://github.com/M-Igashi/mp3rgain/releases/download/v$version/mp3rgain-v$version-windows-arm64.zip"
            }
        },
        "hash": {
            "url": "$url.sha256"
        }
    }
}
