{
    "homepage": "https://github.com/Saratoga-Official/MRA",
    "version": "2.5.5",
    "license": "MIT",
    "hash": "28087f0b99b293ec38bac65b0623e1b4ddfbe58d5d66024fd1fddd039e012727",
    "url": "https://github.com/Saratoga-Official/MRA/releases/download/v2.5.5/MRA-win-x86_64-v2.5.5.zip",
    "checkver": "github",
    "autoupdate": {
        "url": "https://github.com/Saratoga-Official/MRA/releases/download/v$version/MRA-win-x86_64-v$version.zip",
        "extract_dir": "MRA-win-x86_64-v$version"
    },
    "persist": "config",
    "bin": [
        [
            "MRA.exe",
            "maa-mra"
        ]
    ]
}
