{
    "version": "1.20250210143449",
    "architecture": {
        "64bit": {
            "url": "https://github.com/nais/cli/releases/download/1.20250210143449/nais-cli_1.20250210143449_windows_amd64.tar.gz",
            "bin": [
                "nais.exe"
            ],
            "hash": "bb1a168487fda50b084f561c00a4ef90872fc0837b37f6f0debafe95aa9ba47c"
        }
    },
    "homepage": "https://github.com/nais/cli",
    "license": "MIT",
    "description": "Command-line interface for NAIS"
}
