{
    "version": "0.1.50",
    "architecture": {
        "64bit": {
            "url": "https://github.com/nimbus-solution/nimbus-releases/releases/download/v0.1.50/nimbus_0.1.50_windows_amd64.zip",
            "bin": [
                "nimbus.exe"
            ],
            "hash": "270f680ba0778d7819aad61d0bf68ac5ba69db8557bfa41eed3c87a6498887ae"
        },
        "arm64": {
            "url": "https://github.com/nimbus-solution/nimbus-releases/releases/download/v0.1.50/nimbus_0.1.50_windows_arm64.zip",
            "bin": [
                "nimbus.exe"
            ],
            "hash": "0405a663c14ffcf724281d73220a8ca88df257547d351fb19454214e0224ab0e"
        }
    },
    "homepage": "https://testnimbus.dev",
    "license": "MIT",
    "description": "Local Apex test runner for Salesforce developers"
}
