{
    "version": "0.6.0",
    "architecture": {
        "64bit": {
            "url": "https://github.com/xinnjie/onekeymap-cli/releases/download/v0.6.0/onekeymap-cli_Windows_x86_64.zip",
            "bin": [
                "onekeymap-cli.exe"
            ],
            "hash": "3aefe6ea80eb95db7beae1b8d5cfe0ffdb7ea6d4301e89e9e2aed378578bdcaa"
        },
        "arm64": {
            "url": "https://github.com/xinnjie/onekeymap-cli/releases/download/v0.6.0/onekeymap-cli_Windows_arm64.zip",
            "bin": [
                "onekeymap-cli.exe"
            ],
            "hash": "868e307bfaa7167925f12ee78406f84c9bef4d5530062a6dcfca8763115055bc"
        }
    },
    "homepage": "https://github.com/xinnjie/onekeymap-cli",
    "license": "MIT",
    "description": "Universal keymap configuration tool for VSCode, Zed, IntelliJ and more"
}
