{
    "version": "2.12.8.2",
    "description": "Minecraft 启动器 Plain Craft Launcher（PCL）。",
    "homepage": "https://github.com/Meloong-Git/PCL",
    "license": "Freeware",
    "architecture": {
        "64bit": {
            "url": "https://github.com/Meloong-Git/PCL/raw/refs/heads/main/%E6%9C%80%E6%96%B0%E6%AD%A3%E5%BC%8F%E7%89%88.zip",
            "hash": "a37d0d526c98917c65c60956fc464b5e5b6396df8ceb602ea9ca7f41775bb188"
        }
    },
    "bin": "Plain Craft Launcher 2.exe",
    "shortcuts": [
        [
            "Plain Craft Launcher 2.exe",
            "Plain Craft Launcher 2"
        ]
    ],
    "persist": [
        ".minecraft",
        "PCL"
    ],
    "checkver": {
        "url": "https://api.github.com/repos/Meloong-Git/PCL/commits?path=%E6%9C%80%E6%96%B0%E6%AD%A3%E5%BC%8F%E7%89%88.zip",
        "jsonpath": "$[0].commit.message",
        "regex": "([\\d.]+)"
    },
    "autoupdate": {
        "architecture": {
            "64bit": {
                "url": "https://github.com/Meloong-Git/PCL/raw/refs/heads/main/%E6%9C%80%E6%96%B0%E6%AD%A3%E5%BC%8F%E7%89%88.zip"
            }
        }
    }
}
