{
    "$schema": "https://raw.githubusercontent.com/ScoopInstaller/Scoop/master/schema.json",
    "homepage": "https://github.com/edde746/plezy",
    "version": "1.20.0",
    "description": "Modern cross-platform Plex client built with Flutter",
    "license": "GPL-3.0",
    "architecture": {
        "64bit": {
            "url": "https://github.com/edde746/plezy/releases/download/1.20.0/plezy-windows-x64-portable.7z",
            "hash": "0a6113f3910bdb6e5ff777ae440579803036b225a2eb9d655006193c57a0b8b2"
        },
        "arm64": {
            "url": "https://github.com/edde746/plezy/releases/download/1.20.0/plezy-windows-arm64-portable.7z",
            "hash": "0d8da4dab74e13c4ede85c220a1ce7c654912838abebbdd251151a7fa41d24fa"
        }
    },
    "bin": "plezy.exe",
    "shortcuts": [
        [
            "plezy.exe",
            "Plezy"
        ]
    ],
    "persist": "storage",
    "checkver": "github",
    "autoupdate": {
        "architecture": {
            "64bit": {
                "url": "https://github.com/edde746/plezy/releases/download/$version/plezy-windows-x64-portable.7z"
            },
            "arm64": {
                "url": "https://github.com/edde746/plezy/releases/download/$version/plezy-windows-arm64-portable.7z"
            }
        }
    }
}
