{
    "version": "2.0.16+27",
    "description": "A cross-platform live streaming client.",
    "homepage": "https://github.com/liuchuancong/pure_live",
    "license": "AGPL-3.0-only",
    "architecture": {
        "64bit": {
            "url": "https://github.com/liuchuancong/pure_live/releases/download/v2.0.16/PureLive-2.0.16+27-windows-x64.msix#/dl.7z",
            "hash": "0b7be78f4e6bac1b1062942a0b355018c04a35e0429f9aead854c74720ee05c0"
        }
    },
    "bin": "pure_live.exe",
    "shortcuts": [
        [
            "pure_live.exe",
            "Pure Live"
        ]
    ],
    "checkver": {
        "url": "https://api.github.com/repos/liuchuancong/pure_live/releases/latest",
        "jsonpath": "$..assets[*].name",
        "regex": "PureLive-(?<version>[\\d.]+\\+[\\d]+)-windows-x64\\.msix"
    },
    "autoupdate": {
        "architecture": {
            "64bit": {
                "url": "https://github.com/liuchuancong/pure_live/releases/download/v$matchHead/PureLive-$version-windows-x64.msix#/dl.7z"
            }
        }
    }
}
