{
    "version": "0.2.2-beta",
    "description": "A fast, minimal shell prompt for PowerShell.",
    "homepage": "https://github.com/lucaspimentel/pwsh-prompt",
    "license": "MIT",
    "architecture": {
        "64bit": {
            "url": "https://github.com/lucaspimentel/pwsh-prompt/releases/download/v0.2.2-beta/pwsh-prompt-win-x64.zip",
            "hash": "5944f8e68d6b7c1800a1b2780fc9c3d6e3c9a4bcfb6e55da52b5fa4416b09324"
        }
    },
    "bin": "pwsh-prompt.exe",
    "notes": [
        "Add the following to your PowerShell profile to use pwsh-prompt:",
        "",
        "function prompt { & pwsh-prompt }"
    ],
    "checkver": {
        "url": "https://api.github.com/repos/lucaspimentel/pwsh-prompt/releases",
        "jsonpath": "$[0].tag_name",
        "regex": "v([\\d.]+-?[\\w.]*)"
    },
    "autoupdate": {
        "architecture": {
            "64bit": {
                "url": "https://github.com/lucaspimentel/pwsh-prompt/releases/download/v$version/pwsh-prompt-win-x64.zip"
            }
        },
        "hash": {
            "url": "$baseurl/checksums.txt"
        }
    }
}
