{
    "version": "10.1.0-rc2",
    "description": "A generic and open source machine emulator and virtualizer.",
    "homepage": "https://qemu.weilnetz.de/",
    "license": "GPL-2.0-only",
    "architecture": {
        "64bit": {
            "url": "https://qemu.weilnetz.de/w64/2025/qemu-w64-setup-20250806.exe#/dl.7z_",
            "hash": "0202feeeeba4794be1fc5697018d71b546c5c0bfd0a33ea9b408f28646e089fd"
        }
    },
    "pre_install": "Expand-7zipArchive \"$dir\\dl.7z_\" \"$dir\" -Removal -Switches '-xr!*.exe.nsis -x!$PLUGINSDIR'",
    "env_add_path": ".",
    "checkver": "<strong>(?<year>\\d{4})-(?<month>\\d{2})-(?<day>\\d{2})</strong>: New QEMU installer \\((?<version>[\\d.a-z-]+)\\)",
    "autoupdate": {
        "architecture": {
            "64bit": {
                "url": "https://qemu.weilnetz.de/w64/$matchYear/qemu-w64-setup-$matchYear$matchMonth$matchDay.exe#/dl.7z_"
            }
        },
        "hash": {
            "url": "$urlNoExt.sha512"
        }
    }
}
