{
    "version": "1.2.70",
    "license": "AGPL-3.0",
    "url": "https://github.com/goretk/redress/releases/download/v1.2.70/redress-v1.2.70-windows.zip",
    "homepage": "https://github.com/goretk/redress",
    "hash": "59d248ee763948ccc1213c2c9b93c38b90770a59c587513a249d7bb69945f35f",
    "pre_install": "Move-Item -Path \"$dir\\redress-v$version\\redress.exe\" -Destination \"$dir\\redress.exe\"",
    "bin": [
        [
            "redress.exe",
            "redress"
        ]
    ],
    "checkver": "github",
    "autoupdate": {
        "url": "https://github.com/goretk/redress/releases/download/v$version/redress-v$version-windows.zip"
    }
}
