{
    "version": "2.1.3",
    "description": "CLI tool to convert SVG/Android Vector Drawable to Jetpack Compose ImageVector",
    "homepage": "https://www.svgtocompose.com",
    "license": "MIT",
    "architecture": {
        "64bit": {
            "url": "https://github.com/rafaeltonholo/svg-to-compose/releases/download/2.1.3/s2c-mingwX64-binaries.zip",
            "hash": "8adc57d6f310f419ae3d194cd920d051a7c2c97501f3892e746c9ea2a93d7da3",
            "extract_dir": "s2c-mingwX64-binaries"
        }
    },
    "bin": "s2c.exe",
    "checkver": {
        "github": "https://github.com/rafaeltonholo/svg-to-compose"
    },
    "autoupdate": {
        "architecture": {
            "64bit": {
                "url": "https://github.com/rafaeltonholo/svg-to-compose/releases/download/$version/s2c-mingwX64-binaries.zip",
                "extract_dir": "s2c-mingwX64-binaries"
            }
        },
        "hash": {
            "mode": "download"
        }
    }
}
