{
    "version": "0.10.0",
    "architecture": {
        "32bit": {
            "url": "https://github.com/jippi/scm-engine/releases/download/v0.10.0/scm-engine_Windows_i386.zip",
            "bin": [
                "scm-engine.exe"
            ],
            "hash": "a49a0c5a3ba3de904b5af91b3992202468ecda2383d1714a7947f88faecfe877"
        },
        "64bit": {
            "url": "https://github.com/jippi/scm-engine/releases/download/v0.10.0/scm-engine_Windows_x86_64.zip",
            "bin": [
                "scm-engine.exe"
            ],
            "hash": "dca1fc6ac8acf247083bc4a687bc939e72e98d28bad608b6cff108729e5195ea"
        },
        "arm64": {
            "url": "https://github.com/jippi/scm-engine/releases/download/v0.10.0/scm-engine_Windows_arm64.zip",
            "bin": [
                "scm-engine.exe"
            ],
            "hash": "bedc22b7bc14a2b1a29ea78ef3424b1098bbaa6ec99a83aaa4d4e2fc59b4b048"
        }
    },
    "homepage": "https://github.com/jippi/scm-engine",
    "license": "MIT",
    "description": "Make working with .env files easier"
}
