{
    "version": "0.1.1",
    "architecture": {
        "32bit": {
            "url": "https://github.com/jippi/scm-engine/releases/download/v0.1.1/scm-engine_Windows_i386.zip",
            "bin": [
                "scm-engine.exe"
            ],
            "hash": "f9b415b6d96ab7079530033cff3b59373224ed8ed67ca38ed61e9f9219046f3b"
        },
        "64bit": {
            "url": "https://github.com/jippi/scm-engine/releases/download/v0.1.1/scm-engine_Windows_x86_64.zip",
            "bin": [
                "scm-engine.exe"
            ],
            "hash": "05941992df82f49f8f39d57a1f4a83e7e9b7f8b16a1f8dd1474a646b5a93e4c0"
        },
        "arm64": {
            "url": "https://github.com/jippi/scm-engine/releases/download/v0.1.1/scm-engine_Windows_arm64.zip",
            "bin": [
                "scm-engine.exe"
            ],
            "hash": "3828ecb7e237d39430542c9c316575286cf04496e9ec4a755ab926e5ac60e0e5"
        }
    },
    "homepage": "https://github.com/jippi/scm-engine",
    "license": "MIT",
    "description": "Make working with .env files easier"
}
