{
    "version": "10.0.0",
    "description": "Book manager.",
    "homepage": "http://ekakin.la.coocan.jp/shihonp.htm",
    "url": "http://ekakin.la.coocan.jp/download/shihonpv1000.zip",
    "hash": "sha512:971cbd8e63869fd7f0a577fb63572fcd52bd90fe58b6838e516b6312d47412bc26ebf71150bc63b63ed322e901779ae58753dc74e112eddf704e3a00c8c0d5c1",
    "shortcuts": [
        [
            "shihon.exe",
            "私本管理Plus"
        ]
    ],
    "checkver": {
        "url": "http://ekakin.la.coocan.jp/shihonp.htm",
        "regex": "Plus Ver([\\d\\.]+) &gt;&gt; <a href=\"http://awplus.jp/cgi-bin/dl/page\\.cgi\\?symbol"
    }
}
