{
    "homepage": "https://github.com/overflow65537/MAA_SnowBreak",
    "version": "2.8.19",
    "license": "MIT",
    "hash": "953d4de665e29dbaa292b74ea24fa8c1fe4007073233431b487e46ff941a63b5",
    "url": "https://github.com/overflow65537/MAA_SnowBreak/releases/download/v2.8.19/MSBA-win-x86_64-v2.8.19.zip",
    "checkver": "github",
    "autoupdate": {
        "url": "https://github.com/overflow65537/MAA_SnowBreak/releases/download/v$version/MSBA-win-x86_64-v$version.zip",
        "extract_dir": "MSBA-win-x86_64-v$version"
    },
    "persist": "config",
    "bin": [
        [
            "MaaPiCli.exe",
            "maa-snowbreak"
        ]
    ]
}
