{
    "homepage": "https://github.com/overflow65537/MAA_SnowBreak",
    "version": "2.7.54",
    "license": "MIT",
    "hash": "8aebdfdb609b59c302684febc7509a9ed84152ec0d73aeebbabd7cb53a237b53",
    "url": "https://github.com/overflow65537/MAA_SnowBreak/releases/download/v2.7.54/MSBA-win-x86_64-v2.7.54.zip",
    "checkver": "github",
    "autoupdate": {
        "url": "https://github.com/overflow65537/MAA_SnowBreak/releases/download/v$version/MSBA-win-x86_64-v$version.zip",
        "extract_dir": "MSBA-win-x86_64-v$version"
    },
    "persist": "config",
    "bin": [
        [
            "MaaPiCli.exe",
            "maa-snowbreak"
        ]
    ]
}
