{
    "version": "0.4.7",
    "description": "Distributed AI inference node for the Spore network",
    "homepage": "https://sporeintel.com",
    "license": "MIT",
    "architecture": {
        "64bit": {
            "url": "https://api.sporeintel.com/api/releases/0.4.7/windows/x86_64/spore_0_4_fzbg0qucoe.7-windows-x86_64.zip",
            "hash": "83e05055a02f79241ad2c9dcec4e9bfeeec8b86027b4f6a22966684f46c2d332"
        }
    },
    "bin": "spore.exe",
    "checkver": {
        "url": "https://api.sporeintel.com/api/releases/latest/windows/x86_64",
        "jsonpath": "$.version"
    },
    "notes": [
        "To get started with Spore:",
        "  1. Authenticate: spore auth",
        "  2. Start the node: spore start",
        "",
        "For more information, visit https://sporeintel.com/docs"
    ]
}
