{
    "version": "r19-mod-5.7",
    "description": "Editor for VapourSynth scripts. Modified by YomikoR for newer VapourSynth APIs.",
    "homepage": "https://github.com/YomikoR/VapourSynth-Editor",
    "license": "Freeware",
    "url": "https://github.com/YomikoR/VapourSynth-Editor/releases/download/r19-mod-5.7/VapourSynth_Editor-r19-mod-5.7.7z",
    "hash": "a456912b19f61b2bd0c7936e69c72c303589d61ddaf59b4e55077e42fed080c5",
    "shortcuts": [
        [
            "vsedit.exe",
            "VapourSynth-Editor"
        ]
    ],
    "persist": "vsedit.config",
    "checkver": {
        "url": "https://github.com/YomikoR/VapourSynth-Editor/releases/latest",
        "regex": "/releases/tag/(r[\\d]+-mod-[\\d.]+)"
    },
    "autoupdate": {
        "url": "https://github.com/YomikoR/VapourSynth-Editor/releases/download/$version/VapourSynth_Editor-$version.7z"
    }
}
