{
    "version": "1.1.64",
    "description": "A vpinball frontend for Linux, Mac, and Windows (slim)",
    "homepage": "https://github.com/superhac/vpinfe",
    "license": "",
    "architecture": {
        "64bit": {
            "url": "https://github.com/superhac/vpinfe/releases/download/v1.1.64/vpinfe-v1.1.64-win-x64-slim.zip#/vpinfe.zip",
            "hash": "a73f374556ee070be88ae77207b47a3cbe8e874c6a9443c8a4c509da302666d2"
        }
    },
    "bin": "vpinfe/vpinfe.bat",
    "checkver": {
        "github": "https://github.com/superhac/vpinfe"
    },
    "autoupdate": {
        "architecture": {
            "64bit": {
                "url": "https://github.com/superhac/vpinfe/releases/download/v$version/vpinfe-v$version-win-x64-slim.zip#/vpinfe.zip"
            }
        }
    }
}
