{
    "version": "2.4.0",
    "description": "WAFW00F 允许用户识别和识别保护网站的 Web 应用程序防火墙 （WAF） 产品。",
    "homepage": "https://github.com/EnableSecurity/wafw00f",
    "license": "UNKNOWN",
    "suggest": {
        "python": "miniconda3"
    },
    "url": "https://github.com/EnableSecurity/wafw00f/archive/refs/tags/v2.4.0.zip",
    "hash": "927e5804ef05e9090e2365de4e8d9bd3402646bbe4fce0e1f735013dfef5bbb7",
    "post_install": [
        "Move-Item -Path \"$dir\\wafw00f-$version\\*\" -Destination \"$dir\\\"",
        "Remove-Item \"$dir\\wafw00f-$version\" -Force -Recurse",
        "& cmd /c \"call activate python3env && pip install wafw00f -U\""
    ],
    "checkver": "github",
    "autoupdate": {
        "url": "https://github.com/EnableSecurity/wafw00f/archive/refs/tags/v$version.zip"
    }
}
