{
    "version": "1.20250525.0",
    "description": "The JavaScript / Wasm runtime that powers Cloudflare Workers",
    "homepage": "https://github.com/cloudflare/workerd",
    "license": "Apache-2.0",
    "architecture": {
        "64bit": {
            "url": "https://github.com/cloudflare/workerd/releases/download/v1.20250525.0/workerd-windows-64.gz",
            "hash": "735b535e10d160b9cae4ba730aaab7c53631f18c129c2d8065a54a5d77fc92d5"
        }
    },
    "bin": "workerd.exe",
    "checkver": "github",
    "autoupdate": {
        "architecture": {
            "64bit": {
                "url": "https://github.com/cloudflare/workerd/releases/download/v$version/workerd-windows-64.gz"
            }
        }
    }
}
