{
    "version": "2.4.1",
    "description": "",
    "homepage": "https://zcode.z.ai/cn",
    "license": "Proprietary",
    "url": "https://cdn.codegeex.cn/zcode/electron/releases/2.4.1/ZCode-2.4.1-win-x64.exe#/dl.7z",
    "hash": "e511f6a72a6af46b220a6b829fb47eff2489dbadbdf5c8c8ef94052c20c2413d",
    "bin": "zcode.exe",
    "installer": {
        "script": [
            "Expand-7ZipArchive \"$dir\\`$PLUGINSDIR\\app-64.7z\" \"$dir\" -Removal",
            "Remove-Item \"$dir\\`$PLUGINSDIR\",\"$dir\\`$R0\"  -Force -Recurse"
        ]
    },
    "shortcuts": [
        [
            "zcode.exe",
            "ZCode"
        ]
    ],
    "checkver": {
        "url": "https://zcode.z.ai/cn/changelog",
        "regex": ">Release v([\\d.]+)<"
    },
    "autoupdate": {
        "url": "https://cdn.codegeex.cn/zcode/electron/releases/$version/ZCode-$version-win-x64.exe#/dl.7z"
    },
    "notes": "English version is in https://zcode-ai.com"
}
